mooquant_tushare/__init__.py
mooquant_tushare/barfeed.py
mooquant_tushare/common.py
mooquant_tushare/livefeed.py
mooquant_tushare/tools.py
mooquant_tushare-0.2.2.dist-info/METADATA
mooquant_tushare-0.2.2.dist-info/RECORD
mooquant_tushare-0.2.2.dist-info/WHEEL
mooquant_tushare-0.2.2.dist-info/entry_points.txt
mooquant_tushare-0.2.2.dist-info/top_level.txt
