Metadata-Version: 2.1
Name: mooquant-tushare
Version: 0.2.2
Summary: mooquant tushare module
Home-page: https://github.com/bopo/mooquant_tushare
Author: bopo.wang
Author-email: ibopo@126.com
License: MIT license
Keywords: mooquant_tushare
Platform: UNKNOWN
Classifier: Development Status :: 2 - Pre-Alpha
Classifier: Intended Audience :: Developers
Classifier: License :: OSI Approved :: MIT License
Classifier: Natural Language :: English
Classifier: Programming Language :: Python :: 3
Classifier: Programming Language :: Python :: 3.3
Classifier: Programming Language :: Python :: 3.4
Classifier: Programming Language :: Python :: 3.5
Requires-Dist: mooquant
